gaarf_executors/__init__.py
gaarf_executors/api_executor.py
gaarf_executors/bq_executor.py
gaarf_executors/sql_executor.py
gaarf_executors/entrypoints/__init__.py
gaarf_executors/entrypoints/utils.py
gaarf_executors/entrypoints/cli/__init__.py
gaarf_executors/entrypoints/cli/api.py
gaarf_executors/entrypoints/cli/bq.py
gaarf_executors/entrypoints/cli/gaarf.py
gaarf_executors/entrypoints/cli/sql.py
gaarf_executors-0.0.1.dist-info/METADATA
gaarf_executors-0.0.1.dist-info/WHEEL
gaarf_executors-0.0.1.dist-info/entry_points.txt
gaarf_executors-0.0.1.dist-info/top_level.txt
gaarf_executors-0.0.1.dist-info/RECORD
